<?xml version="1.0" encoding="UTF-8"?>
<!DOCTYPE note PUBLIC "-//OASIS//DTD DocBook XML V4.5//EN"
"http://www.oasis-open.org/docbook/xml/4.3/docbookx.dtd">
<!-- AUTO-GENERATED FILE. DO NOT EDIT. -->
<note lang="de" revision=": 0 $">

  <formalpara>
    <title>Interner Hilfetext zu dieser Applikation in Asterisk 1.4:</title>

    <para><screen lang="en-US">  -= Info about application &apos;MeetMeAdmin&apos; =-

[Synopsis]
MeetMe conference Administration

[Description]
  MeetMeAdmin(confno,command[,user]): Run admin command for conference
      &apos;e&apos; -- Eject last user that joined
      &apos;k&apos; -- Kick one user out of conference
      &apos;K&apos; -- Kick all users out of conference
      &apos;l&apos; -- Unlock conference
      &apos;L&apos; -- Lock conference
      &apos;m&apos; -- Unmute one user
      &apos;M&apos; -- Mute one user
      &apos;n&apos; -- Unmute all users in the conference
      &apos;N&apos; -- Mute all non-admin users in the conference
      &apos;r&apos; -- Reset one user&apos;s volume settings
      &apos;R&apos; -- Reset all users volume settings
      &apos;s&apos; -- Lower entire conference speaking volume
      &apos;S&apos; -- Raise entire conference speaking volume
      &apos;t&apos; -- Lower one user&apos;s talk volume
      &apos;T&apos; -- Raise one user&apos;s talk volume
      &apos;u&apos; -- Lower one user&apos;s listen volume
      &apos;U&apos; -- Raise one user&apos;s listen volume
      &apos;v&apos; -- Lower entire conference listening volume
      &apos;V&apos; -- Raise entire conference listening volume</screen></para>
  </formalpara>

  <formalpara>
    <title>Differenz des internen Hilfetexts von Asterisk 1.2 zu 1.4:</title>

    <para><screen lang="en-US" language="diff-u">--- in Asterisk 1.2
+++ in Asterisk 1.4
@@ -10,7 +10,17 @@
         &apos;K&apos; -- Kick all users out of conference
         &apos;l&apos; -- Unlock conference
         &apos;L&apos; -- Lock conference
-        &apos;m&apos; -- Unmute conference
-        &apos;M&apos; -- Mute conference
-        &apos;n&apos; -- Unmute entire conference (except admin)
-        &apos;N&apos; -- Mute entire conference (except admin)
+        &apos;m&apos; -- Unmute one user
+        &apos;M&apos; -- Mute one user
+        &apos;n&apos; -- Unmute all users in the conference
+        &apos;N&apos; -- Mute all non-admin users in the conference
+        &apos;r&apos; -- Reset one user&apos;s volume settings
+        &apos;R&apos; -- Reset all users volume settings
+        &apos;s&apos; -- Lower entire conference speaking volume
+        &apos;S&apos; -- Raise entire conference speaking volume
+        &apos;t&apos; -- Lower one user&apos;s talk volume
+        &apos;T&apos; -- Raise one user&apos;s talk volume
+        &apos;u&apos; -- Lower one user&apos;s listen volume
+        &apos;U&apos; -- Raise one user&apos;s listen volume
+        &apos;v&apos; -- Lower entire conference listening volume
+        &apos;V&apos; -- Raise entire conference listening volume</screen></para>
  </formalpara>

  <formalpara>
    <title>Differenz des internen Hilfetexts von Asterisk 1.4 zu 1.6:</title>

    <para>- keine -</para>
  </formalpara>

</note>
