<?xml version="1.0" encoding="UTF-8"?>
<!DOCTYPE note PUBLIC "-//OASIS//DTD DocBook XML V4.5//EN"
"http://www.oasis-open.org/docbook/xml/4.3/docbookx.dtd">
<!-- AUTO-GENERATED FILE. DO NOT EDIT. -->
<note lang="de" revision="$Revision$">

  <formalpara>
    <title>Asterisk-Versionen:</title>

    <para><literallayout class="monospaced">&#x00A0;&#x00A0;&#x00A0;&#x00A0;&#x00A0;&#x00A0;&#x00A0;&#x00A0;|&#x00A0;&#x00A0;&#x00A0;&#x00A0;&#x00A0;|&#x00A0;&#x00A0;&#x00A0;&#x00A0;&#x00A0;&#x00A0;&#x00A0;&#x00A0;|&#x00A0;&#x00A0;&#x00A0;&#x00A0;&#x00A0;|&#x00A0;&#x00A0;&#x00A0;&#x00A0;&#x00A0;&#x00A0;&#x00A0;&#x00A0;|&#x00A0;<emphasis role="bold">1.6</emphasis>&#x00A0;|&#x2014;&#x2014;&#x2014;&#x2014;&#x2014;&#x2014;&#x2014;&#x2014;</literallayout></para>
  </formalpara>

  <formalpara>
    <title>Interner Hilfetext zu dieser Applikation in Asterisk 1.6:</title>

    <para><screen lang="en-US">  -= Info about application &apos;MinivmGreet&apos; =-

[Synopsis]
Play Mini-Voicemail prompts

[Description]
  MinivmGreet(username@domain[,options]):
This application is part of the Mini-Voicemail system, configured in minivm.conf.
MinivmGreet() plays default prompts or user specific prompts for an account.
Busy and unavailable messages can be choosen, but will be overridden if a temporary
message exists for the account.

Result is given in channel variable MINIVM_GREET_STATUS
        The possible values are:     SUCCESS | USEREXIT | FAILED

  Options:
    b    - Play the &apos;busy&apos; greeting to the calling party.
    s    - Skip the playback of instructions for leaving a message to the
           calling party.
    u    - Play the &apos;unavailable greeting.</screen></para>
  </formalpara>

  <formalpara>
    <title>Differenz des internen Hilfetexts von Asterisk 1.4 zu 1.6:</title>

    <para>&#8211; in Asterisk 1.4 nicht vorhanden &#8211;</para>
  </formalpara>

</note>
