<?xml version="1.0" encoding="UTF-8"?>
<!DOCTYPE note PUBLIC "-//OASIS//DTD DocBook XML V4.5//EN"
"http://www.oasis-open.org/docbook/xml/4.3/docbookx.dtd">
<!-- AUTO-GENERATED FILE. DO NOT EDIT. -->
<note lang="en" revision="$Revision$">

  <formalpara>
    <title>Internal help for this application in Asterisk 1.4:</title>

    <para><screen lang="en-US">  -= Info about application &apos;ChanIsAvail&apos; =-

[Synopsis]
Check channel availability

[Description]
  ChanIsAvail(Technology/resource[&amp;Technology2/resource2...][|options]):
This application will check to see if any of the specified channels are
available. The following variables will be set by this application:
  ${AVAILCHAN}     - the name of the available channel, if one exists
  ${AVAILORIGCHAN} - the canonical channel name that was used to create the channel
  ${AVAILSTATUS}   - the status code for the available channel
  Options:
    s - Consider the channel unavailable if the channel is in use at all
    j - Support jumping to priority n+101 if no channel is available</screen></para>
  </formalpara>

  <formalpara>
    <title>Diff of the internal help from Asterisk 1.2 to 1.4:</title>

    <para>- none -</para>
  </formalpara>

  <formalpara>
    <title>Diff of the internal help from Asterisk 1.4 to 1.6:</title>

    <para><screen lang="en-US" language="diff-u">--- in Asterisk 1.4
+++ in Asterisk 1.6
@@ -4,12 +4,15 @@
   Check channel availability

   [Description]
-    ChanIsAvail(Technology/resource[&amp;Technology2/resource2...][|options]):
+    ChanIsAvail(Technology/resource[&amp;Technology2/resource2...][,options]):
   This application will check to see if any of the specified channels are
-  available. The following variables will be set by this application:
-    ${AVAILCHAN}     - the name of the available channel, if one exists
-    ${AVAILORIGCHAN} - the canonical channel name that was used to create the channel
-    ${AVAILSTATUS}   - the status code for the available channel
+  available.
     Options:
-      s - Consider the channel unavailable if the channel is in use at all
-      j - Support jumping to priority n+101 if no channel is available
+      a - Check for all available channels, not only the first one.
+      s - Consider the channel unavailable if the channel is in use at all.
+      t - Simply checks if specified channels exist in the channel list
+          (implies option s).
+  This application sets the following channel variable upon completion:
+    AVAILCHAN     - the name of the available channel, if one exists
+    AVAILORIGCHAN - the canonical channel name that was used to create the channel
+    AVAILSTATUS   - the status code for the available channel</screen></para>
  </formalpara>

</note>
