<?xml version="1.0" encoding="UTF-8"?>
<!DOCTYPE note PUBLIC "-//OASIS//DTD DocBook XML V4.5//EN"
"http://www.oasis-open.org/docbook/xml/4.3/docbookx.dtd">
<!-- AUTO-GENERATED FILE. DO NOT EDIT. -->
<note lang="en" revision="$Revision$">

  <formalpara>
    <title>Asterisk versions:</title>

    <para><literallayout class="monospaced">&#x2014;&#x2014;&#x2014;&#x2014;&#x2014;&#x2014;&#x2014;&#x2014;|&#x00A0;<emphasis role="bold">1.2</emphasis>&#x00A0;|&#x2014;&#x2014;&#x2014;&#x2014;&#x2014;&#x2014;&#x2014;&#x2014;|&#x00A0;<emphasis role="bold">1.4</emphasis>&#x00A0;|&#x2014;&#x2014;&#x2014;&#x2014;&#x2014;&#x2014;&#x2014;&#x2014;|&#x00A0;<emphasis role="bold">1.6</emphasis>&#x00A0;|&#x2014;&#x2014;&#x2014;&#x2014;&#x2014;&#x2014;&#x2014;&#x2014;</literallayout></para>
  </formalpara>

  <formalpara>
    <title>Internal help for this application in Asterisk 1.4:</title>

    <para><screen lang="en-US">  -= Info about application &apos;SIPAddHeader&apos; =-

[Synopsis]
Add a SIP header to the outbound call

[Description]
  SIPAddHeader(Header: Content)
Adds a header to a SIP call placed with DIAL.
Remember to user the X-header if you are adding non-standard SIP
headers, like &quot;X-Asterisk-Accountcode:&quot;. Use this with care.
Adding the wrong headers may jeopardize the SIP dialog.
Always returns 0</screen></para>
  </formalpara>

  <formalpara>
    <title>Diff of the internal help from Asterisk 1.2 to 1.4:</title>

    <para>- none -</para>
  </formalpara>

  <formalpara>
    <title>Diff of the internal help from Asterisk 1.4 to 1.6:</title>

    <para><screen lang="en-US" language="diff-u">--- in Asterisk 1.4
+++ in Asterisk 1.6
@@ -4,7 +4,7 @@
   Add a SIP header to the outbound call

   [Description]
-    SIPAddHeader(Header: Content)
+    SIPAddHeader(Header: Content):
   Adds a header to a SIP call placed with DIAL.
   Remember to user the X-header if you are adding non-standard SIP
   headers, like &quot;X-Asterisk-Accountcode:&quot;. Use this with care.</screen></para>
  </formalpara>

</note>
